handlebar_python/__init__.py
handlebar_python-0.1.0.dist-info/WHEEL
handlebar_python-0.1.0.dist-info/METADATA
handlebar_python-0.1.0.dist-info/RECORD
