Metadata-Version: 2.3
Name: handlebar-python
Version: 0.1.0
Summary: Core governance layer for handlebar (https://gethandlebar.com)
Keywords: governance,ai,agent
Author: Handlebar Team
Author-email: Handlebar Team <contact@gethandlebar.com>
Requires-Python: >=3.13
Project-URL: Homepage, https://gethandlebar.com
Project-URL: Issues, https://github.com/gethandlebar/handlebar-python/issues
Project-URL: Repository, https://github.com/gethandlebar/handlebar-python
